{
  "address": "string",
  "ageReqLower": 0,
  "ageReqUpper": 0,
  "alias": "string",
  "bgImg": "string",
  "bgVedio": "string",
  "contactName": "string",
  "defaultContactType": 0,
  "eachSubscribeCostScore": 0,
  "eduReq": 0,
  "enterprise": true,
  "enterpriseName": "string",
  "enterpriseNo": "string",
  "heightReqLower": 0,
  "heightReqUpper": 0,
  "industry": "string",
  "logo": "string",
  "miniWechat": "string",
  "mobile": "string",
  "onlineSubscribeNum": 0,
  "onlineTime": "2022-05-20T07:24:20.793Z",
  "onlineWeights": 0,
  "orders": 0,
  "personDescp": "string",
  "personLogo": "string",
  "personName": "string",
  "position": "string",
  "postDetail": "string",
  "postId": 0,
  "postListDetail": "string",
  "postType": 0,
  "qq": "string",
  "recruitNum": 0,
  "recruitUserId": 0,
  "salary": "string",
  "settleType": 0,
  "sexReq": 0,
  "status": 0,
  "subscribeId": 0,
  "subScribeNum": 0,
  "subscribeNum": 0,
  "subscribeStatus": 0,
  "scribeCreateAt":"2022-04-20 20:02:49",
  "tags": "string",
  "tagsKc": "string",
  "tips": "string",
  "title": "string",
  "trainTips": "string",
  "userSubscribeNum": 0,
  "wechat": "string",
  "workAddress": "string",
  "workArea": "string",
  "workCity": "string",
  "workDate": "string",
  "workForm": 0,
  "workTime": "string"
}